{"cameraMode":{"drawMode":0,"name":"Shaded","section":"Shading Mode"},"sceneLighting":true,"audioPlay":false,"sceneViewState":{"m_AlwaysRefresh":false,"showFog":true,"showSkybox":true,"showFlares":true,"showImageEffects":true,"showParticleSystems":true,"showVisualEffectGraphs":true,"m_FxEnabled":true},"in2DMode":false,"pivot":{"x":-253.60072326660157,"y":2.1255905628204347,"z":1047.818359375},"rotation":{"x":0.0841374471783638,"y":0.03935721516609192,"z":0.0036292453296482565,"w":-0.9959632158279419},"size":0.14424021542072297,"orthographic":false}